saphyr/__init__.py
saphyr/async_helper.py
saphyr/cli.py
saphyr/dev.py
saphyr/server.py
saphyr-0.0.1.dist-info/METADATA
saphyr-0.0.1.dist-info/RECORD
saphyr-0.0.1.dist-info/WHEEL
saphyr-0.0.1.dist-info/top_level.txt
