Metadata-Version: 2.1
Name: saphyr
Version: 0.0.1
Summary: An experiemental fullstack framework
Home-page: https://github.com/laibulle/saphyr
Author: Guillaume Bailleul
Author-email: laibulle@gmail.com
License: UNKNOWN
Platform: UNKNOWN
Classifier: Programming Language :: Python :: 3
Classifier: License :: OSI Approved :: MIT License
